tooport/__init__.py
tooport-0.0.1.dist-info/METADATA
tooport-0.0.1.dist-info/WHEEL
tooport-0.0.1.dist-info/top_level.txt
tooport-0.0.1.dist-info/RECORD
