Metadata-Version: 2.4
Name: tooport
Version: 0.0.1
Summary: TooPort: To Operate Open-world (TOO) Commercial Platform.
Author-email: Your Name <admin@tooport.com>
Project-URL: Homepage, https://tooport.com
Project-URL: Bug Tracker, https://github.com/tooport/tooport/issues
Classifier: Programming Language :: Python :: 3
Classifier: License :: OSI Approved :: MIT License
Classifier: Operating System :: OS Independent
Requires-Python: >=3.7
